README.md
setup.cfg
setup.py
eltch/__init__.py
eltch/eltch.py
eltch.egg-info/PKG-INFO
eltch.egg-info/SOURCES.txt
eltch.egg-info/dependency_links.txt
eltch.egg-info/not-zip-safe
eltch.egg-info/top_level.txt