Metadata-Version: 1.0
Name: eltch
Version: 0.9.1
Summary: Electrotechnical assistant.
Home-page: UNKNOWN
Author: UNKNOWN
Author-email: officialdyomshin@gmail.ru
License: UNKNOWN
Platform: UNKNOWN
